LICENSE
README.md
setup.py
py_snowflake_id.egg-info/PKG-INFO
py_snowflake_id.egg-info/SOURCES.txt
py_snowflake_id.egg-info/dependency_links.txt
py_snowflake_id.egg-info/top_level.txt
snowflake/__init__.py
snowflake/snowflake.py